README.rst
setup.cfg
setup.py
freetv/__init__.py
freetv/projectFreeTV.py
freetv/show.py
freetv/test.py
freetv/util.py
project_free_tv.egg-info/PKG-INFO
project_free_tv.egg-info/SOURCES.txt
project_free_tv.egg-info/dependency_links.txt
project_free_tv.egg-info/pbr.json
project_free_tv.egg-info/requires.txt
project_free_tv.egg-info/top_level.txt