Metadata-Version: 1.0
Name: project-free-tv
Version: 0.2.5
Summary: Unoffical Project Free TV API
Home-page: https://github.com/gnijuohz/Project-Free-TV-API
Author: Jing Zhou
Author-email: gnijuohz@gmail.com
License: MIT
Platform: UNKNOWN
